[
	{
		"id": "1",
		"title": "paper pouch",
		"rating": "4",
		"price": "46.00",
		"img": "../assets//products-imgs/product-img-1.jpg",
		"amount": "1"
	},
	{
		"id": "2",
		"title": "paper bag",
		"rating": "5",
		"price": "79.00",
		"img": "../assets//products-imgs/product-img-2.jpg",
		"amount": "1"
	},
	{
		"id": "3",
		"title": "plastic pouch",
		"rating": "5",
		"price": "27.00",
		"img": "../assets//products-imgs/product-img-3.jpg",
		"amount": "1"
	},
	{
		"id": "4",
		"title": "coffee pot",
		"rating": "4",
		"price": "71.00",
		"img": "../assets//products-imgs/product-img-4.jpg",
		"amount": "1"
	},
	{
		"id": "5",
		"title": "tea pot",
		"rating": "5",
		"price": "54.00",
		"img": "../assets//products-imgs/product-img-5.jpg",
		"amount": "1"
	},
	{
		"id": "6",
		"title": "paper cup",
		"rating": "4",
		"price": "31.00",
		"img": "../assets//products-imgs/product-img-6.jpg",
		"amount": "1"
	}
]
